zen_models/__init__.py
zen_models/zen_models.py
zen_models-0.0.2.dist-info/METADATA
zen_models-0.0.2.dist-info/WHEEL
zen_models-0.0.2.dist-info/top_level.txt
zen_models-0.0.2.dist-info/RECORD
