Metadata-Version: 2.1
Name: zen-models
Version: 0.0.2
Summary: The zen models Python package is an internal package for zenerate team. It contains all the models which will be common to different microservices and could be used in all of them
Home-page: UNKNOWN
Author: Ravi Shankar Vats
Author-email: ravisvats@gmail.com
License: MIT
Keywords: models zenerate naehas
Platform: UNKNOWN
Requires-Dist: SQLAlchemy
